kvuilder/__init__.py
kvuilder/command.py
kvuilder/data/__init__.py
kvuilder-1.0.1.dist-info/LICENSE
kvuilder-1.0.1.dist-info/METADATA
kvuilder-1.0.1.dist-info/WHEEL
kvuilder-1.0.1.dist-info/entry_points.txt
kvuilder-1.0.1.dist-info/top_level.txt
kvuilder-1.0.1.dist-info/RECORD
